coreadaptor/AuthAdaptor.py
coreadaptor/IonosCoreProxy.py
coreadaptor/__init__.py
ionosenterprise/__init__.py
ionosenterprise/client.py
ionosenterprise/errors.py
ionosenterprise/utils.py
ionosenterprise/items/__init__.py
ionosenterprise/items/backupunit.py
ionosenterprise/items/datacenter.py
ionosenterprise/items/firewall.py
ionosenterprise/items/group.py
ionosenterprise/items/ipblock.py
ionosenterprise/items/lan.py
ionosenterprise/items/loadbalancer.py
ionosenterprise/items/nic.py
ionosenterprise/items/privatecrossconnect.py
ionosenterprise/items/server.py
ionosenterprise/items/snapshot.py
ionosenterprise/items/user.py
ionosenterprise/items/volume.py
ionosenterprise/requests/__init__.py
ionosenterprise/requests/backupunit.py
ionosenterprise/requests/cdrom.py
ionosenterprise/requests/contract.py
ionosenterprise/requests/datacenter.py
ionosenterprise/requests/dicts.py
ionosenterprise/requests/firewall.py
ionosenterprise/requests/group.py
ionosenterprise/requests/image.py
ionosenterprise/requests/ipblock.py
ionosenterprise/requests/k8s.py
ionosenterprise/requests/k8s_config.py
ionosenterprise/requests/k8s_nodepools.py
ionosenterprise/requests/lan.py
ionosenterprise/requests/loadbalancer.py
ionosenterprise/requests/location.py
ionosenterprise/requests/nic.py
ionosenterprise/requests/pccs.py
ionosenterprise/requests/request.py
ionosenterprise/requests/resource.py
ionosenterprise/requests/s3key.py
ionosenterprise/requests/server.py
ionosenterprise/requests/share.py
ionosenterprise/requests/snapshot.py
ionosenterprise/requests/user.py
ionosenterprise/requests/volume.py
ionosenterprise-5.5.0.dist-info/LICENSE
ionosenterprise-5.5.0.dist-info/METADATA
ionosenterprise-5.5.0.dist-info/WHEEL
ionosenterprise-5.5.0.dist-info/top_level.txt
ionosenterprise-5.5.0.dist-info/RECORD
