Metadata-Version: 2.1
Name: ionosenterprise
Version: 5.5.0
Summary: IonosEnterprise API Client Library for Python
Home-page: https://github.com/ionos-enterprise/ionos-enterprise-sdk-python
Author: Ionos Enterprise
Author-email: sdk@cloud.ionos.com
License: Apache 2.0
Keywords: ionos enterprise api client cloud
Platform: any
Classifier: Development Status :: 5 - Production/Stable
Classifier: Natural Language :: English
Classifier: Environment :: Web Environment
Classifier: Intended Audience :: Developers
Classifier: License :: OSI Approved :: Apache Software License
Classifier: Operating System :: POSIX
Classifier: Programming Language :: Python
Classifier: Programming Language :: Python :: 2
Classifier: Programming Language :: Python :: 3
Classifier: Topic :: Software Development :: Libraries :: Python Modules
Classifier: Topic :: Software Development :: Libraries :: Application Frameworks
Classifier: Topic :: Internet :: WWW/HTTP
Requires-Dist: requests (>=2.0.0)
Requires-Dist: six (>=1.10.0)
Requires-Dist: appdirs (>=1.4.3)
Requires-Dist: ionoscloud (>=5.0.3)
Provides-Extra: testing
Requires-Dist: pytest ; extra == 'testing'
